regmean_imputer/__init__.py
regmean_imputer/impute_column.py
regmean_imputer-0.1.0.dist-info/METADATA
regmean_imputer-0.1.0.dist-info/WHEEL
regmean_imputer-0.1.0.dist-info/RECORD
