Metadata-Version: 2.1
Name: regmean-imputer
Version: 0.1.0
Summary: Regularized mean imputation functions for imputing numerical data by grouped categoricals
License: MIT
Author: Christopher Carroll Smith
Author-email: 75859865+chriscarrollsmith@users.noreply.github.com
Requires-Python: >=3.11,<3.13
Classifier: License :: OSI Approved :: MIT License
Classifier: Programming Language :: Python :: 3
Classifier: Programming Language :: Python :: 3.11
Requires-Dist: numpy (>=1.26.1,<2.0.0)
Requires-Dist: pandas (>=2.1.1,<3.0.0)
Requires-Dist: scikit-learn (>=1.3.2,<2.0.0)
